ipypathchooser/__init__.py
ipypathchooser/_version.py
ipypathchooser/double_click_select.py
ipypathchooser/pathchooser.py
ipypathchooser/utils.py
ipypathchooser/static/extension.js
ipypathchooser/static/index.js
ipypathchooser/static/index.js.map
ipypathchooser-0.1.0a0.data/data/etc/jupyter/nbconfig/notebook.d/ipypathchooser.json
ipypathchooser-0.1.0a0.data/data/share/jupyter/nbextensions/ipypathchooser/extension.js
ipypathchooser-0.1.0a0.data/data/share/jupyter/nbextensions/ipypathchooser/index.js
ipypathchooser-0.1.0a0.data/data/share/jupyter/nbextensions/ipypathchooser/index.js.map
ipypathchooser-0.1.0a0.dist-info/METADATA
ipypathchooser-0.1.0a0.dist-info/WHEEL
ipypathchooser-0.1.0a0.dist-info/top_level.txt
ipypathchooser-0.1.0a0.dist-info/RECORD
